[{
    "id": 0,
    "type": "Hammer",
    "price": 3
}, {
    "id": 1,
    "type": "Nail",
    "price": 1
}, {
    "id": 2,
    "type": "Screwdriver",
    "price": 8
}, {
    "id": 3,
    "type": "Screw",
    "price": 2
}, {
    "id": 4,
    "type": "Plane",
    "price": 10
}, {
    "id": 5,
    "type": "Saw",
    "price": 6
}, {
    "id": 6,
    "type": "Jigsaw",
    "price": 20
}, {
    "id": 7,
    "type": "Circular Saw",
    "price": 30
}, {
    "id": 8,
    "type": "Welder",
    "price": 40
}, {
    "id": 9,
    "type": "Laser Cutter",
    "price": 100
}, {
    "id": 10,
    "type": "Robot",
    "price": 500
}]